singular_server_updater/__init__.py
singular_server_updater/management/__init__.py
singular_server_updater/management/commands/__init__.py
singular_server_updater/management/commands/update_server.py
singular_server_updater/routes/__init__.py
singular_server_updater/routes/routes.py
singular_server_updater/webhooks/__init__.py
singular_server_updater/webhooks/webhooks.py
singular_server_updater-0.0.8.dist-info/METADATA
singular_server_updater-0.0.8.dist-info/WHEEL
singular_server_updater-0.0.8.dist-info/top_level.txt
singular_server_updater-0.0.8.dist-info/RECORD
