Metadata-Version: 2.1
Name: singular-server-updater
Version: 0.0.8
Summary: Server updater
Home-page: https://lucas@bitbucket.org/singular-dev/server_updater.git
Author: Singular Sistemas
Author-email: ivan@singular.inf.br
License: UNKNOWN
Platform: UNKNOWN
Requires-Python: >=3.6
Requires-Dist: django
Requires-Dist: fabric
Requires-Dist: invoke
Requires-Dist: django-crontab
Requires-Dist: singular-dbbackup-sender
